{
  "generated": "2026-06-12",
  "total_documents": 855,
  "total_pages": 599,
  "ecommerce_menu_pages": 167,
  "ui_prototype_pages": 432,
  "documents_by_module": {
    "platform": 62,
    "api": 2,
    "core": 29,
    "database": 7,
    "deployment": 10,
    "framework": 6,
    "README.md": 1,
    "accounting": 2,
    "ai": 9,
    "bi-system": 2,
    "booking": 2,
    "crm": 2,
    "data-warehouse": 2,
    "documents": 2,
    "ecommerce": 200,
    "fleet": 2,
    "helpdesk": 2,
    "hr": 2,
    "knowledge": 2,
    "logistics": 2,
    "manufacturing": 2,
    "marketplace": 2,
    "payroll": 2,
    "pos": 2,
    "project": 2,
    "purchase": 2,
    "sales": 2,
    "subscription": 2,
    "timesheet": 2,
    "qa": 11,
    "roadmap": 4,
    "ui-prototype": 433,
    "ui-ux": 40,
    "workflows": 1
  }
}